heatmappy/__init__.py
heatmappy/heatmap.py
heatmappy/video.py
heatmappy/assets/450pxdot.png
heatmappy/assets/SampleVideo_720x480_1mb.mp4
heatmappy/assets/cat.jpg
heatmappy/assets/default.png
heatmappy/assets/reveal.png
heatmappy-0.2.6.dist-info/DESCRIPTION.rst
heatmappy-0.2.6.dist-info/METADATA
heatmappy-0.2.6.dist-info/RECORD
heatmappy-0.2.6.dist-info/WHEEL
heatmappy-0.2.6.dist-info/metadata.json
heatmappy-0.2.6.dist-info/top_level.txt
