Metadata-Version: 2.0
Name: heatmappy
Version: 0.2.6
Summary: Draw image heatmaps in python
Home-page: https://github.com/LumenResearch/heatmappy
Author: Lumen Research
Author-email: development@lumen-research.com
License: UNKNOWN
Download-URL: https://github.com/LumenResearch/heatmappy/tarball/0.1.1
Keywords: image,heatmap,heat map
Platform: UNKNOWN
Classifier: Programming Language :: Python :: 3
Requires-Dist: Pillow (==3.0.0)
Requires-Dist: cycler (==0.9.0)
Requires-Dist: matplotlib (==1.5.0)
Requires-Dist: moviepy (==0.2.2.11)
Requires-Dist: numpy (==1.10.1)
Requires-Dist: pyparsing (==2.0.6)
Requires-Dist: python-dateutil (==2.4.2)
Requires-Dist: pytz (==2015.7)
Requires-Dist: six (==1.10.0)
Requires-Dist: wheel (==0.24.0)
